pymetranet/__init__.py
pymetranet/cmd_line_params.py
pymetranet/geo_reference.py
pymetranet/libpymetranet.so
pymetranet/linker.py
pymetranet/lzw_c.py
pymetranet/msx_serializer.py
pymetranet/msx_serializer_v1.py
pymetranet/msx_serializer_v2.py
pymetranet/polar_data.py
pymetranet/product_data.py
pymetranet/product_file.py
pymetranet/version.py
pymetranet/volumesweep.py
pymetranet/volumesweep_serializer.py
pymetranet/xml_util.py
pymetranet-0.3.1.data/scripts/cmdlineparse.py
pymetranet-0.3.1.data/scripts/compuncomp.py
pymetranet-0.3.1.data/scripts/geodata.py
pymetranet-0.3.1.data/scripts/import_pymetranet.py
pymetranet-0.3.1.data/scripts/linkproduct.py
pymetranet-0.3.1.data/scripts/msxdump.py
pymetranet-0.3.1.data/scripts/polardata.py
pymetranet-0.3.1.data/scripts/readproduct.py
pymetranet-0.3.1.data/scripts/sweepinfo.py
pymetranet-0.3.1.data/scripts/writeproduct.py
pymetranet-0.3.1.dist-info/LICENSE
pymetranet-0.3.1.dist-info/METADATA
pymetranet-0.3.1.dist-info/WHEEL
pymetranet-0.3.1.dist-info/top_level.txt
pymetranet-0.3.1.dist-info/RECORD
