Metadata-Version: 2.1
Name: pymetranet
Version: 0.3.1
Summary: Python Metranet library
Home-page: https://www.eldesradar.com
Author: Eldes
Author-email: info@eldes.t
License: BSD-3-Clause license
Keywords: pymetranet
Classifier: License :: OSI Approved :: BSD License
Classifier: Natural Language :: English
Classifier: Programming Language :: Python :: 3.7
License-File: LICENSE
Requires-Dist: numpy
